matplotlib2tikz/__about__.py
matplotlib2tikz/__init__.py
matplotlib2tikz/axes.py
matplotlib2tikz/color.py
matplotlib2tikz/files.py
matplotlib2tikz/image.py
matplotlib2tikz/legend.py
matplotlib2tikz/line2d.py
matplotlib2tikz/patch.py
matplotlib2tikz/path.py
matplotlib2tikz/quadmesh.py
matplotlib2tikz/save.py
matplotlib2tikz/text.py
matplotlib2tikz/util.py
matplotlib2tikz-0.7.6.dist-info/METADATA
matplotlib2tikz-0.7.6.dist-info/WHEEL
matplotlib2tikz-0.7.6.dist-info/top_level.txt
matplotlib2tikz-0.7.6.dist-info/RECORD
