Metadata-Version: 2.1
Name: matplotlib2tikz
Version: 0.7.6
Summary: Convert matplotlib figures into TikZ/PGFPlots
Home-page: https://github.com/nschloe/matplotlib2tikz
Author: Nico Schlömer
Author-email: nico.schloemer@gmail.com
License: License :: OSI Approved :: MIT License
Platform: UNKNOWN
Classifier: Development Status :: 5 - Production/Stable
Classifier: License :: OSI Approved :: MIT License
Classifier: Operating System :: OS Independent
Classifier: Programming Language :: Python
Classifier: Programming Language :: Python :: 3
Classifier: Topic :: Multimedia :: Graphics :: Graphics Conversion
Classifier: Topic :: Scientific/Engineering :: Visualization
Provides-Extra: all
Provides-Extra: update
